yadsl/__init__.py
yadsl/_adsl.py
yadsl-0.0.3.dist-info/LICENSE
yadsl-0.0.3.dist-info/METADATA
yadsl-0.0.3.dist-info/WHEEL
yadsl-0.0.3.dist-info/RECORD
