Metadata-Version: 2.1
Name: yadsl
Version: 0.0.3
Summary: yadsl is a simple Python module to easily fetch data from https://adsl.yemen.net.ye official website.
Home-page: https://github.com/omamkaz/yadsl
License: GPL-3.0
Keywords: yemen,adsl,internet,balance,check,web,scrape,bs4,script
Author: Osama Mohammed Al-zabidi
Author-email: omamkaz@gmail.com
Requires-Python: >=3.7,<3.13
Classifier: License :: OSI Approved :: GNU General Public License v3 (GPLv3)
Classifier: Programming Language :: Python :: 3
Classifier: Programming Language :: Python :: 3.7
Classifier: Programming Language :: Python :: 3.8
Classifier: Programming Language :: Python :: 3.9
Classifier: Programming Language :: Python :: 3.10
Classifier: Programming Language :: Python :: 3.11
Classifier: Programming Language :: Python :: 3.12
Requires-Dist: argparse (==1.4.0)
Requires-Dist: beautifulsoup4 (==4.11.1)
Requires-Dist: requests (==2.31.0)
Project-URL: Repository, https://github.com/omamkaz/yadsl
